fxcalc/__init__.py
fxcalc/main.py
fxcalc-0.1.1.dist-info/METADATA
fxcalc-0.1.1.dist-info/WHEEL
fxcalc-0.1.1.dist-info/licenses/LICENSE.txt
fxcalc-0.1.1.dist-info/RECORD
