Metadata-Version: 2.4
Name: fxcalc
Version: 0.1.1
Summary: calculator
Author-email: euquisox <n9star007@gmail.com>
License-File: LICENSE.txt
Classifier: License :: OSI Approved :: MIT License
Classifier: Operating System :: OS Independent
Classifier: Programming Language :: Python :: 3
Requires-Python: >=3.11.0
